yesgraph.py
yesgraph-0.6.6.dist-info/DESCRIPTION.rst
yesgraph-0.6.6.dist-info/METADATA
yesgraph-0.6.6.dist-info/metadata.json
yesgraph-0.6.6.dist-info/RECORD
yesgraph-0.6.6.dist-info/top_level.txt
yesgraph-0.6.6.dist-info/WHEEL
