Metadata-Version: 2.0
Name: yesgraph
Version: 0.6.6
Summary: Python wrapper for the YesGraph API.
Home-page: https://github.com/yesgraph/python-yesgraph
Author: YesGraph
Author-email: team@yesgraph.com
License: UNKNOWN
Platform: any
Classifier: Development Status :: 4 - Beta
Classifier: Intended Audience :: Developers
Classifier: License :: OSI Approved :: MIT License
Classifier: Programming Language :: Python :: 2.7
Classifier: Programming Language :: Python :: 3.4
Classifier: Programming Language :: Python :: Implementation :: CPython
Classifier: Programming Language :: Python :: Implementation :: PyPy
Classifier: Topic :: Software Development
Requires-Dist: requests
Requires-Dist: six
